<?xml version = '1.0' encoding = 'UTF-8'?>
<Diagram class="oracle.dbtools.crest.swingui.logical.DPVLogical" name="Logical" id="FFED35BA-D5F6-2D4B-DF46-481F21490E16">
<createdBy>limra</createdBy>
<modifiedBy>limra</modifiedBy>
<createdTime>2021-11-05 15:14:43 UTC</createdTime>
<autoRoute>false</autoRoute>
<boxInbox>true</boxInbox>
<showLegend>false</showLegend>
<showLabels>false</showLabels>
<showRelAttributes>false</showRelAttributes>
<gridEnabled>false</gridEnabled>
<showGrid>false</showGrid>
<diagramColor>-1</diagramColor>
<display>false</display>
<notation>1</notation>
<objectViews>
<OView class="oracle.dbtools.crest.swingui.logical.TVEntity" oid="0A86062D-C59E-02C5-C57A-BC98BD067932" otype="Entity" vid="7538619B-BCB8-EAA1-716B-6C2E1945D983">
<hideElementsInCurrentOnly>false</hideElementsInCurrentOnly>
<bounds x="92" y="636" width="142" height="102"/>
</OView>
<OView class="oracle.dbtools.crest.swingui.logical.TVEntity" oid="0AD0B471-E5CE-FF1D-CCD3-1ECC2F1611A8" otype="Entity" vid="59CC2302-E728-A2D8-008F-BCFDFDB540ED">
<hideElementsInCurrentOnly>false</hideElementsInCurrentOnly>
<bounds x="477" y="498" width="181" height="58"/>
</OView>
<OView class="oracle.dbtools.crest.swingui.logical.TVEntity" oid="19B547E1-48A7-15BD-C197-E4ADAC804F4B" otype="Entity" vid="51988641-6939-E706-EDD0-CF13CBD1983B">
<hideElementsInCurrentOnly>false</hideElementsInCurrentOnly>
<bounds x="95" y="502" width="143" height="57"/>
</OView>
<OView class="oracle.dbtools.crest.swingui.logical.TVEntity" oid="2A63DC72-5B22-9896-7AB2-631A8C44C640" otype="Entity" vid="96D032F5-3DDF-674C-42A8-C2B624741C56">
<hideElementsInCurrentOnly>false</hideElementsInCurrentOnly>
<bounds x="343" y="137" width="172" height="89"/>
</OView>
<OView class="oracle.dbtools.crest.swingui.logical.TVEntity" oid="4A968E06-3504-1CEC-7BAB-E60C8535F817" otype="Entity" vid="EBFB3210-DE90-202D-E6E9-91402CC0E15A">
<hideElementsInCurrentOnly>false</hideElementsInCurrentOnly>
<bounds x="186" y="33" width="341" height="209"/>
</OView>
<OView class="oracle.dbtools.crest.swingui.logical.TVEntity" oid="4D0D55C0-DBCC-56A5-69D9-CCEC6B278A4D" otype="Entity" vid="8870E5D4-CF66-BF8A-7477-9C360E27BC36">
<hideElementsInCurrentOnly>false</hideElementsInCurrentOnly>
<bounds x="1097" y="639" width="138" height="102"/>
</OView>
<OView class="oracle.dbtools.crest.swingui.logical.TVEntity" oid="57C20E25-54AB-1C05-F3EB-B12BC2A0CFC4" otype="Entity" vid="B127EB2F-1DE5-5E85-9B58-3EE9E690AA5F">
<hideElementsInCurrentOnly>false</hideElementsInCurrentOnly>
<bounds x="55" y="17" width="508" height="241"/>
</OView>
<OView class="oracle.dbtools.crest.swingui.logical.TVEntity" oid="5965668A-2970-9347-5C88-CCFE3797FFA7" otype="Entity" vid="5ED4CE8F-34D1-4A54-268C-03BEEE0CF4C1">
<hideElementsInCurrentOnly>false</hideElementsInCurrentOnly>
<bounds x="770" y="32" width="140" height="87"/>
</OView>
<OView class="oracle.dbtools.crest.swingui.logical.TVEntity" oid="8BB74EC4-418E-6754-389F-E8F6126D57EF" otype="Entity" vid="D1614F23-13E2-9FDA-962B-EE91F9DC55AE">
<hideElementsInCurrentOnly>false</hideElementsInCurrentOnly>
<bounds x="778" y="365" width="118" height="72"/>
</OView>
<OView class="oracle.dbtools.crest.swingui.logical.TVEntity" oid="9B106322-48FA-07F0-C47B-0CC5808D167E" otype="Entity" vid="8CD3FBD0-61DE-7BB3-0F8A-BEF385E4B512">
<hideElementsInCurrentOnly>false</hideElementsInCurrentOnly>
<bounds x="525" y="638" width="135" height="102"/>
</OView>
<OView class="oracle.dbtools.crest.swingui.logical.TVEntity" oid="9D0F79AB-8247-ADFA-67F3-B57E82187E00" otype="Entity" vid="8B09019D-ECA9-2D09-5AE6-002AB3B4DDD4">
<hideElementsInCurrentOnly>false</hideElementsInCurrentOnly>
<bounds x="1088" y="359" width="142" height="132"/>
</OView>
<OView class="oracle.dbtools.crest.swingui.logical.TVEntity" oid="C7D5A8D1-A68A-5310-2604-1DE7F0CEF4C4" otype="Entity" vid="D9A55F92-2F37-DE8A-F008-7A010C5362BC">
<hideElementsInCurrentOnly>false</hideElementsInCurrentOnly>
<bounds x="343" y="53" width="145" height="74"/>
</OView>
<OView class="oracle.dbtools.crest.swingui.logical.TVEntity" oid="F130C2CE-0636-2F72-0207-8EC1DA761993" otype="Entity" vid="7C48C224-6DD4-6755-FF09-610D3AC09C91">
<hideElementsInCurrentOnly>false</hideElementsInCurrentOnly>
<bounds x="106" y="361" width="124" height="27"/>
</OView>
<OView class="oracle.dbtools.crest.swingui.logical.TVEntity" oid="F184D8F9-68BE-FA6F-64BF-A6FE0D450CBD" otype="Entity" vid="B03E892D-A577-CC6B-1A61-F90941FB6364">
<hideElementsInCurrentOnly>false</hideElementsInCurrentOnly>
<bounds x="786" y="636" width="111" height="102"/>
</OView>
<OView class="oracle.dbtools.crest.swingui.logical.TVEntity" oid="FCB34F8C-1401-5F3F-2880-C34887EE8DA5" otype="Entity" vid="BBA7AD81-FE8C-4B33-5263-D3177E6CF82A">
<hideElementsInCurrentOnly>false</hideElementsInCurrentOnly>
<bounds x="776" y="204" width="137" height="87"/>
</OView>
<OView class="oracle.dbtools.crest.swingui.logical.TVEntity" oid="FD991F24-BA7B-4E2D-9035-CDAB3DD856DE" otype="Entity" vid="7934B76F-11FB-7F42-47C9-749978E1E39D">
<hideElementsInCurrentOnly>false</hideElementsInCurrentOnly>
<bounds x="293" y="672" width="159" height="42"/>
</OView>
</objectViews>
<connectors>
<Connector class="oracle.dbtools.crest.swingui.logical.TVInheritanceRelation" oid="03A634B0-E6C8-EB1F-D27F-4D60F5BCA5CB" otype="Hierarchy relation" vid_source="EBFB3210-DE90-202D-E6E9-91402CC0E15A" vid_target="D9A55F92-2F37-DE8A-F008-7A010C5362BC">
<hideElementsInCurrentOnly>false</hideElementsInCurrentOnly>
<backgroundColor>-65536</backgroundColor>
<lineWidth>1</lineWidth>
</Connector>
<Connector class="oracle.dbtools.crest.swingui.logical.TVRelation" oid="081BB60D-37D3-A275-0EDA-808C58E1DDD2" otype="Relation" vid_source="8870E5D4-CF66-BF8A-7477-9C360E27BC36" vid_target="B03E892D-A577-CC6B-1A61-F90941FB6364">
<hideElementsInCurrentOnly>false</hideElementsInCurrentOnly>
<backgroundColor>-16777216</backgroundColor>
<lineWidth>1</lineWidth>
<points>
<point x="1097" y="703"/>
<point x="897" y="703"/>
</points>
</Connector>
<Connector class="oracle.dbtools.crest.swingui.logical.TVRelation" oid="19A2E551-6014-ECD9-39FB-3FE8C83430CE" otype="Relation" vid_source="D1614F23-13E2-9FDA-962B-EE91F9DC55AE" vid_target="BBA7AD81-FE8C-4B33-5263-D3177E6CF82A">
<hideElementsInCurrentOnly>false</hideElementsInCurrentOnly>
<backgroundColor>-16777216</backgroundColor>
<lineWidth>1</lineWidth>
<points>
<point x="862" y="365"/>
<point x="862" y="291"/>
</points>
</Connector>
<Connector class="oracle.dbtools.crest.swingui.logical.TVRelation" oid="1E3316A2-A74F-DAC5-50D6-621268A9D956" otype="Relation" vid_source="B127EB2F-1DE5-5E85-9B58-3EE9E690AA5F" vid_target="7C48C224-6DD4-6755-FF09-610D3AC09C91">
<hideElementsInCurrentOnly>false</hideElementsInCurrentOnly>
<backgroundColor>-16777216</backgroundColor>
<lineWidth>1</lineWidth>
<points>
<point x="168" y="258"/>
<point x="168" y="361"/>
</points>
</Connector>
<Connector class="oracle.dbtools.crest.swingui.logical.TVRelation" oid="3DAFBDA7-87E0-4164-7553-33D4E5A46056" otype="Relation" vid_source="8870E5D4-CF66-BF8A-7477-9C360E27BC36" vid_target="B03E892D-A577-CC6B-1A61-F90941FB6364">
<hideElementsInCurrentOnly>false</hideElementsInCurrentOnly>
<backgroundColor>-16777216</backgroundColor>
<lineWidth>1</lineWidth>
<points>
<point x="1097" y="688"/>
<point x="897" y="688"/>
</points>
</Connector>
<Connector class="oracle.dbtools.crest.swingui.logical.TVRelation" oid="444C860C-A1F6-3F40-5487-FBDAAF6F8CE4" otype="Relation" vid_source="EBFB3210-DE90-202D-E6E9-91402CC0E15A" vid_target="BBA7AD81-FE8C-4B33-5263-D3177E6CF82A">
<hideElementsInCurrentOnly>false</hideElementsInCurrentOnly>
<backgroundColor>-16777216</backgroundColor>
<lineWidth>1</lineWidth>
<points>
<point x="527" y="223"/>
<point x="776" y="223"/>
</points>
</Connector>
<Connector class="oracle.dbtools.crest.swingui.logical.TVRelation" oid="45879BB7-A557-6D37-354F-44E95A171E65" otype="Relation" vid_source="5ED4CE8F-34D1-4A54-268C-03BEEE0CF4C1" vid_target="BBA7AD81-FE8C-4B33-5263-D3177E6CF82A">
<hideElementsInCurrentOnly>false</hideElementsInCurrentOnly>
<backgroundColor>-16777216</backgroundColor>
<lineWidth>1</lineWidth>
<points>
<point x="858" y="119"/>
<point x="858" y="204"/>
</points>
</Connector>
<Connector class="oracle.dbtools.crest.swingui.logical.TVRelation" oid="58714B46-264E-AAE1-B9E7-C8ABDCD55950" otype="Relation" vid_source="7538619B-BCB8-EAA1-716B-6C2E1945D983" vid_target="7934B76F-11FB-7F42-47C9-749978E1E39D">
<hideElementsInCurrentOnly>false</hideElementsInCurrentOnly>
<backgroundColor>-16777216</backgroundColor>
<lineWidth>1</lineWidth>
<points>
<point x="234" y="693"/>
<point x="293" y="693"/>
</points>
</Connector>
<Connector class="oracle.dbtools.crest.swingui.logical.TVRelation" oid="708FA195-F53C-5E42-FC0C-4D327227F369" otype="Relation" vid_source="B03E892D-A577-CC6B-1A61-F90941FB6364" vid_target="59CC2302-E728-A2D8-008F-BCFDFDB540ED">
<hideElementsInCurrentOnly>false</hideElementsInCurrentOnly>
<backgroundColor>-16777216</backgroundColor>
<lineWidth>1</lineWidth>
<points>
<point x="786" y="654"/>
<point x="617" y="556"/>
</points>
</Connector>
<Connector class="oracle.dbtools.crest.swingui.logical.TVRelation" oid="7CC623C2-B94F-F779-B78A-F587F12EAC48" otype="Relation" vid_source="8CD3FBD0-61DE-7BB3-0F8A-BEF385E4B512" vid_target="B03E892D-A577-CC6B-1A61-F90941FB6364">
<hideElementsInCurrentOnly>false</hideElementsInCurrentOnly>
<backgroundColor>-16777216</backgroundColor>
<lineWidth>1</lineWidth>
<points>
<point x="660" y="688"/>
<point x="786" y="688"/>
</points>
</Connector>
<Connector class="oracle.dbtools.crest.swingui.logical.TVInheritanceRelation" oid="7E0F86C8-875C-ACC1-2E82-F2B5D5AE542A" otype="Hierarchy relation" vid_source="B127EB2F-1DE5-5E85-9B58-3EE9E690AA5F" vid_target="EBFB3210-DE90-202D-E6E9-91402CC0E15A">
<hideElementsInCurrentOnly>false</hideElementsInCurrentOnly>
<backgroundColor>-65536</backgroundColor>
<lineWidth>1</lineWidth>
</Connector>
<Connector class="oracle.dbtools.crest.swingui.logical.TVRelation" oid="83EAD4EF-56BC-D488-D949-84C0095543AA" otype="Relation" vid_source="51988641-6939-E706-EDD0-CF13CBD1983B" vid_target="7C48C224-6DD4-6755-FF09-610D3AC09C91">
<hideElementsInCurrentOnly>false</hideElementsInCurrentOnly>
<backgroundColor>-16777216</backgroundColor>
<lineWidth>1</lineWidth>
<points>
<point x="168" y="502"/>
<point x="168" y="388"/>
</points>
</Connector>
<Connector class="oracle.dbtools.crest.swingui.logical.TVRelation" oid="B68AB4AE-09EC-9097-E14B-5187BD49D6E2" otype="Relation" vid_source="D1614F23-13E2-9FDA-962B-EE91F9DC55AE" vid_target="8B09019D-ECA9-2D09-5AE6-002AB3B4DDD4">
<hideElementsInCurrentOnly>false</hideElementsInCurrentOnly>
<backgroundColor>-16777216</backgroundColor>
<lineWidth>1</lineWidth>
<points>
<point x="896" y="420"/>
<point x="1088" y="420"/>
</points>
</Connector>
<Connector class="oracle.dbtools.crest.swingui.logical.TVRelation" oid="CD39EDA2-A1AE-FA92-86DA-8B29C50412C7" otype="Relation" vid_source="B127EB2F-1DE5-5E85-9B58-3EE9E690AA5F" vid_target="59CC2302-E728-A2D8-008F-BCFDFDB540ED">
<hideElementsInCurrentOnly>false</hideElementsInCurrentOnly>
<backgroundColor>-16777216</backgroundColor>
<lineWidth>1</lineWidth>
<points>
<point x="520" y="258"/>
<point x="520" y="498"/>
</points>
</Connector>
<Connector class="oracle.dbtools.crest.swingui.logical.TVRelation" oid="E6064C09-B83B-8DAD-B782-A0C0B329E9E6" otype="Relation" vid_source="8CD3FBD0-61DE-7BB3-0F8A-BEF385E4B512" vid_target="7934B76F-11FB-7F42-47C9-749978E1E39D">
<hideElementsInCurrentOnly>false</hideElementsInCurrentOnly>
<backgroundColor>-16777216</backgroundColor>
<lineWidth>1</lineWidth>
<points>
<point x="525" y="693"/>
<point x="452" y="693"/>
</points>
</Connector>
<Connector class="oracle.dbtools.crest.swingui.logical.TVInheritanceRelation" oid="E9C49C1F-9DB3-A2BD-9603-69640BEAB3E0" otype="Hierarchy relation" vid_source="EBFB3210-DE90-202D-E6E9-91402CC0E15A" vid_target="96D032F5-3DDF-674C-42A8-C2B624741C56">
<hideElementsInCurrentOnly>false</hideElementsInCurrentOnly>
<backgroundColor>-65536</backgroundColor>
<lineWidth>1</lineWidth>
</Connector>
<Connector class="oracle.dbtools.crest.swingui.logical.TVRelation" oid="F1126870-C15B-2F04-A2D7-738A16FED845" otype="Relation" vid_source="5ED4CE8F-34D1-4A54-268C-03BEEE0CF4C1" vid_target="B127EB2F-1DE5-5E85-9B58-3EE9E690AA5F">
<hideElementsInCurrentOnly>false</hideElementsInCurrentOnly>
<backgroundColor>-16777216</backgroundColor>
<lineWidth>1</lineWidth>
<points>
<point x="770" y="90"/>
<point x="563" y="90"/>
</points>
</Connector>
</connectors>
</Diagram>